dataScienceTree/__init__.py
dataScienceTree/cli.py
dataScienceTree/template/__init__.py
dataScienceTree/template/cookiecutter.json
dataScienceTree/template/hooks/post_gen_project.py
dataScienceTree/template/hooks/pre_gen_project.py
dataScienceTree/template/{{cookiecutter.project_slug}}/.dockerignore
dataScienceTree/template/{{cookiecutter.project_slug}}/.gitignore
dataScienceTree/template/{{cookiecutter.project_slug}}/.pre-commit-config.yaml
dataScienceTree/template/{{cookiecutter.project_slug}}/.pypirc
dataScienceTree/template/{{cookiecutter.project_slug}}/__main__.py
dataScienceTree/template/{{cookiecutter.project_slug}}/CHANGELOG.md
dataScienceTree/template/{{cookiecutter.project_slug}}/Dockerfile
dataScienceTree/template/{{cookiecutter.project_slug}}/mkdocs.yml
dataScienceTree/template/{{cookiecutter.project_slug}}/pip.conf
dataScienceTree/template/{{cookiecutter.project_slug}}/requirements.txt
dataScienceTree/template/{{cookiecutter.project_slug}}/ruff.toml
dataScienceTree/template/{{cookiecutter.project_slug}}/src/__init__.py
dataScienceTree/template/{{cookiecutter.project_slug}}/tests/__init__.py
dataScienceTree/template/{{cookiecutter.project_slug}}/tox.ini
datasciencetree-0.2.4.dist-info/entry_points.txt
datasciencetree-0.2.4.dist-info/LICENSE
datasciencetree-0.2.4.dist-info/METADATA
datasciencetree-0.2.4.dist-info/WHEEL
datasciencetree-0.2.4.dist-info/RECORD
