Metadata-Version: 2.1
Name: dataScienceTree
Version: 0.2.4
Summary: Herramienta CLI para inicializar estructura de carpetas para EDA y ML
Home-page: https://github.com/tuusuario/dstree
License: MIT
Author: Juan_Maniglia
Author-email: 90753457+JuanManiglia@users.noreply.github.com
Requires-Python: >=3.10
Classifier: License :: OSI Approved :: MIT License
Classifier: Programming Language :: Python :: 3
Classifier: Programming Language :: Python :: 3.10
Classifier: Programming Language :: Python :: 3.11
Classifier: Programming Language :: Python :: 3.12
Classifier: Programming Language :: Python :: 3.13
Requires-Dist: click (>=8.1.7,<9.0.0)
Requires-Dist: cookiecutter (>=2.6.0,<3.0.0)
Requires-Dist: pre-commit (>=4.0.1,<5.0.0)
Requires-Dist: questionary (>=2.0.1,<3.0.0)
Requires-Dist: rich (>=13.9.4,<14.0.0)
Requires-Dist: ruff (>=0.8.3,<0.9.0)
